[
  {"SkillId":10101,"Name":"攻击","CooldownMs":190010101},
  {"SkillId":10102,"Name":"攻击","CooldownMs":190010102},
  {"SkillId":10201,"Name":"攻击","CooldownMs":190010201},
  {"SkillId":10202,"Name":"攻击","CooldownMs":190010202},
  {"SkillId":10301,"Name":"攻击","CooldownMs":190010301},
  {"SkillId":10302,"Name":"攻击","CooldownMs":190010302},
  {"SkillId":201001011,"Name":"普通攻击","CooldownMs":0},
  {"SkillId":201002011,"Name":"普通攻击","CooldownMs":0},
  {"SkillId":201002012,"Name":"二连击","CooldownMs":0},
  {"SkillId":201003001,"Name":"普通攻击","CooldownMs":0},
  {"SkillId":201003002,"Name":"快速二连击","CooldownMs":0},
  {"SkillId":201007001,"Name":"普通攻击","CooldownMs":0},
  {"SkillId":201007002,"Name":"蓄力挑飞","CooldownMs":0},
  {"SkillId":201007003,"Name":"连打","CooldownMs":0},
  {"SkillId":201007004,"Name":"真普通攻击","CooldownMs":0},
  {"SkillId":201007005,"Name":"真蓄力挑飞","CooldownMs":0},
  {"SkillId":201007006,"Name":"真连打","CooldownMs":0},
  {"SkillId":201004011,"Name":"普通攻击","CooldownMs":0},
  {"SkillId":201004012,"Name":"蓄力射击","CooldownMs":0},
  {"SkillId":201005001,"Name":"普通攻击","CooldownMs":0},
  {"SkillId":201005002,"Name":"蓄力射击","CooldownMs":0},
  {"SkillId":201006001,"Name":"普通攻击","CooldownMs":0},
  {"SkillId":201006002,"Name":"蓄力射击","CooldownMs":0},
  {"SkillId":202001001,"Name":"普通攻击","CooldownMs":0},
  {"SkillId":202002001,"Name":"普通攻击","CooldownMs":0},
  {"SkillId":202003001,"Name":"普通攻击","CooldownMs":0},
  {"SkillId":202003002,"Name":"二连拳","CooldownMs":0},
  {"SkillId":202004001,"Name":"普通攻击","CooldownMs":0},
  {"SkillId":202004002,"Name":"飞斧","CooldownMs":0},
  {"SkillId":214001011,"Name":"普通攻击","CooldownMs":0},
  {"SkillId":214001012,"Name":"突袭","CooldownMs":0},
  {"SkillId":203001001,"Name":"普通攻击","CooldownMs":0},
  {"SkillId":203002011,"Name":"普通攻击","CooldownMs":0},
  {"SkillId":203003001,"Name":"普通攻击","CooldownMs":0},
  {"SkillId":204001001,"Name":"普通攻击","CooldownMs":0},
  {"SkillId":204002001,"Name":"普通攻击","CooldownMs":0},
  {"SkillId":204003001,"Name":"普通攻击","CooldownMs":0},
  {"SkillId":204003002,"Name":"冲锋","CooldownMs":0},
  {"SkillId":205001001,"Name":"普通攻击","CooldownMs":0},
  {"SkillId":205002001,"Name":"普通攻击","CooldownMs":0},
  {"SkillId":205003001,"Name":"普通攻击","CooldownMs":0},
  {"SkillId":205004001,"Name":"普通攻击","CooldownMs":0},
  {"SkillId":206001001,"Name":"普通攻击","CooldownMs":0},
  {"SkillId":206002001,"Name":"普通攻击","CooldownMs":0},
  {"SkillId":206003001,"Name":"普通攻击","CooldownMs":0},
  {"SkillId":206004001,"Name":"普通攻击","CooldownMs":0},
  {"SkillId":206004002,"Name":"二连击","CooldownMs":0},
  {"SkillId":208001001,"Name":"普通攻击","CooldownMs":0},
  {"SkillId":209001001,"Name":"普通攻击","CooldownMs":0},
  {"SkillId":209003001,"Name":"普通攻击","CooldownMs":0},
  {"SkillId":211001001,"Name":"普通攻击","CooldownMs":0},
  {"SkillId":211002001,"Name":"普通攻击","CooldownMs":0},
  {"SkillId":211003001,"Name":"普通攻击","CooldownMs":0},
  {"SkillId":211003002,"Name":"火球","CooldownMs":0},
  {"SkillId":211004001,"Name":"普通攻击","CooldownMs":0},
  {"SkillId":213001001,"Name":"普通攻击","CooldownMs":0},
  {"SkillId":213002001,"Name":"普通攻击","CooldownMs":0},
  {"SkillId":213003001,"Name":"普通攻击","CooldownMs":0},
  {"SkillId":213004001,"Name":"普通攻击","CooldownMs":0},
  {"SkillId":216001001,"Name":"普通攻击","CooldownMs":0},
  {"SkillId":207001001,"Name":"普通攻击","CooldownMs":0},
  {"SkillId":207001002,"Name":"下压","CooldownMs":0},
  {"SkillId":207002001,"Name":"普通攻击","CooldownMs":0},
  {"SkillId":207002002,"Name":"下压","CooldownMs":0},
  {"SkillId":207003001,"Name":"普通攻击","CooldownMs":0},
  {"SkillId":207003002,"Name":"下压","CooldownMs":0},
  {"SkillId":207003003,"Name":"冲锋","CooldownMs":0},
  {"SkillId":210001001,"Name":"普通攻击","CooldownMs":0},
  {"SkillId":210002001,"Name":"普通攻击","CooldownMs":0},
  {"SkillId":210003001,"Name":"普通攻击","CooldownMs":0},
  {"SkillId":210004001,"Name":"普通攻击","CooldownMs":0},
  {"SkillId":200801001,"Name":"普通攻击","CooldownMs":0},
  {"SkillId":59260001,"Name":"普攻击中回血","CooldownMs":159260001},
  {"SkillId":25010001,"Name":"受到的伤害总加成","CooldownMs":0},
  {"SkillId":2000001,"Name":"怒气技能变身","CooldownMs":6200107},
  {"SkillId":3000001,"Name":"怪物-免疫燃烧、迟缓、麻痹、中毒","CooldownMs":0},
  {"SkillId":4000001,"Name":"起身技","CooldownMs":1911100},
  {"SkillId":11101,"Name":"攻击","CooldownMs":1911101},
  {"SkillId":30001,"Name":"烈焰斩","CooldownMs":1930001},
  {"SkillId":30011,"Name":"强化烈焰斩","CooldownMs":1930001},
  {"SkillId":30002,"Name":"烈焰冲锋","CooldownMs":1930002},
  {"SkillId":30012,"Name":"旋身斩","CooldownMs":1930002},
  {"SkillId":30022,"Name":"烈焰不息","CooldownMs":1930002},
  {"SkillId":30003,"Name":"地火裂斩","CooldownMs":1930003},
  {"SkillId":300031,"Name":"地火裂斩","CooldownMs":1930003},
  {"SkillId":30013,"Name":"双重地火","CooldownMs":1930003},
  {"SkillId":300131,"Name":"双重地火","CooldownMs":1930003},
  {"SkillId":30023,"Name":"强化地火","CooldownMs":1930003},
  {"SkillId":300231,"Name":"强化地火","CooldownMs":1930003},
  {"SkillId":30004,"Name":"爆裂斩","CooldownMs":1930004},
  {"SkillId":30014,"Name":"强化爆裂斩","CooldownMs":1930004},
  {"SkillId":30024,"Name":"烈焰裁决","CooldownMs":1930004},
  {"SkillId":30005,"Name":"烈焰火环","CooldownMs":1930005},
  {"SkillId":30101,"Name":"点燃","CooldownMs":0},
  {"SkillId":30111,"Name":"点燃","CooldownMs":1930111},
  {"SkillId":31001,"Name":"火焰掌","CooldownMs":1931001},
  {"SkillId":31011,"Name":"强化火焰掌","CooldownMs":1931001},
  {"SkillId":31002,"Name":"火焰爆冲","CooldownMs":1931002},
  {"SkillId":31012,"Name":"火焰爆炸","CooldownMs":1931002},
  {"SkillId":31022,"Name":"火焰连冲","CooldownMs":1931002},
  {"SkillId":31003,"Name":"熔岩喷发","CooldownMs":1931003},
  {"SkillId":310031,"Name":"熔岩喷发","CooldownMs":1931003},
  {"SkillId":31013,"Name":"多重喷发","CooldownMs":1931003},
  {"SkillId":310131,"Name":"多重喷发","CooldownMs":1931003},
  {"SkillId":31023,"Name":"喷发加剧","CooldownMs":1931003},
  {"SkillId":310231,"Name":"喷发加剧","CooldownMs":1931003},
  {"SkillId":31004,"Name":"爆裂炎爪","CooldownMs":1931004},
  {"SkillId":31014,"Name":"强化爆裂","CooldownMs":1931004},
  {"SkillId":31024,"Name":"焚灭强敌","CooldownMs":1931004},
  {"SkillId":31005,"Name":"龙息审判","CooldownMs":1931005},
  {"SkillId":31101,"Name":"火炎吞噬","CooldownMs":0},
  {"SkillId":31111,"Name":"火炎吞噬","CooldownMs":1931111},
  {"SkillId":10001,"Name":"【测试】冲锋","CooldownMs":0},
  {"SkillId":10002,"Name":"【测试】闪避","CooldownMs":0},
  {"SkillId":40001,"Name":"碎冰斩","CooldownMs":1940001},
  {"SkillId":40011,"Name":"碎冰狂斩","CooldownMs":1940001},
  {"SkillId":40002,"Name":"极寒侵袭","CooldownMs":1940002},
  {"SkillId":40012,"Name":"极寒原点","CooldownMs":1940002},
  {"SkillId":40022,"Name":"极度冰寒","CooldownMs":1940002},
  {"SkillId":40003,"Name":"冰山斩","CooldownMs":1940003},
  {"SkillId":400031,"Name":"冰山斩特效","CooldownMs":1940003},
  {"SkillId":40013,"Name":"冰山重影","CooldownMs":1940003},
  {"SkillId":400131,"Name":"冰山重影特效","CooldownMs":1940003},
  {"SkillId":40023,"Name":"极地悲歌","CooldownMs":1940003},
  {"SkillId":400231,"Name":"极地悲歌特效","CooldownMs":1940003},
  {"SkillId":40004,"Name":"冰雾瞬斩","CooldownMs":1940004},
  {"SkillId":40014,"Name":"冰雾幻斩","CooldownMs":1940004},
  {"SkillId":40024,"Name":"冰雾寒潮","CooldownMs":1940004},
  {"SkillId":40005,"Name":"永冻挽歌","CooldownMs":1940005},
  {"SkillId":40101,"Name":"霜咬","CooldownMs":0},
  {"SkillId":40111,"Name":"霜咬","CooldownMs":1940111},
  {"SkillId":41001,"Name":"冰刃","CooldownMs":1941001},
  {"SkillId":41011,"Name":"暴雨冰刃","CooldownMs":1941001},
  {"SkillId":41002,"Name":"冰矛","CooldownMs":1941002},
  {"SkillId":41012,"Name":"凛冽之矛","CooldownMs":1941002},
  {"SkillId":41022,"Name":"透骨之矛","CooldownMs":1941002},
  {"SkillId":41003,"Name":"冰牢","CooldownMs":1941003},
  {"SkillId":410031,"Name":"冰牢特效","CooldownMs":1941003},
  {"SkillId":41013,"Name":"漫长清算","CooldownMs":1941003},
  {"SkillId":410131,"Name":"漫长清算特效","CooldownMs":1941003},
  {"SkillId":41023,"Name":"全景冰狱","CooldownMs":1941003},
  {"SkillId":410231,"Name":"全景冰狱特效","CooldownMs":1941003},
  {"SkillId":41004,"Name":"冰峰","CooldownMs":1941004},
  {"SkillId":41014,"Name":"冰峰融毁","CooldownMs":1941004},
  {"SkillId":41024,"Name":"冷峰断绝","CooldownMs":1941004},
  {"SkillId":41005,"Name":"霜寒地狱","CooldownMs":1941005},
  {"SkillId":41101,"Name":"深度坏死","CooldownMs":0},
  {"SkillId":41111,"Name":"深度坏死","CooldownMs":1941111},
  {"SkillId":50001,"Name":"闪光震击","CooldownMs":1950001},
  {"SkillId":50011,"Name":"闪光连打","CooldownMs":1950001},
  {"SkillId":50002,"Name":"迅电斩","CooldownMs":1950002},
  {"SkillId":50012,"Name":"二重电斩","CooldownMs":1950002},
  {"SkillId":50022,"Name":"迅电猛斩","CooldownMs":1950002},
  {"SkillId":50003,"Name":"闪电剑旋","CooldownMs":1950003},
  {"SkillId":500031,"Name":"闪电剑旋特效","CooldownMs":1950003},
  {"SkillId":50013,"Name":"剑旋天诛","CooldownMs":1950003},
  {"SkillId":500131,"Name":"剑旋天诛特效","CooldownMs":1950003},
  {"SkillId":50023,"Name":"旋剑霆威","CooldownMs":1950003},
  {"SkillId":500231,"Name":"旋剑霆威特效","CooldownMs":1950003},
  {"SkillId":50004,"Name":"极电剑舞","CooldownMs":1950004},
  {"SkillId":50014,"Name":"极光剑舞","CooldownMs":1950004},
  {"SkillId":50024,"Name":"电光火石","CooldownMs":1950004},
  {"SkillId":50005,"Name":"电殛万方","CooldownMs":1950005},
  {"SkillId":50101,"Name":"导电","CooldownMs":0},
  {"SkillId":50111,"Name":"导电","CooldownMs":1950111},
  {"SkillId":51001,"Name":"雷涌","CooldownMs":1951001},
  {"SkillId":51011,"Name":"雷涌爆发","CooldownMs":1951001},
  {"SkillId":51002,"Name":"雷暴","CooldownMs":1951002},
  {"SkillId":51012,"Name":"雷罚","CooldownMs":1951002},
  {"SkillId":51022,"Name":"雷暴连锁","CooldownMs":1951002},
  {"SkillId":51003,"Name":"雷枪","CooldownMs":1951003},
  {"SkillId":510031,"Name":"雷枪特效","CooldownMs":1951003},
  {"SkillId":51013,"Name":"引动天雷","CooldownMs":1951003},
  {"SkillId":510131,"Name":"引动天雷特效","CooldownMs":1951003},
  {"SkillId":51023,"Name":"天雷灌注","CooldownMs":1951003},
  {"SkillId":510231,"Name":"天雷灌注特效","CooldownMs":1951003},
  {"SkillId":51004,"Name":"雷霆天诛","CooldownMs":1951004},
  {"SkillId":51014,"Name":"雷霆盛怒","CooldownMs":1951004},
  {"SkillId":51024,"Name":"一瞬即逝","CooldownMs":1951004},
  {"SkillId":51005,"Name":"诸神黄昏","CooldownMs":1951005},
  {"SkillId":51101,"Name":"雷极风暴","CooldownMs":0},
  {"SkillId":51111,"Name":"雷极风暴","CooldownMs":1951111},
  {"SkillId":60001,"Name":"淬毒斩","CooldownMs":1960001},
  {"SkillId":60011,"Name":"裂魂毒斩","CooldownMs":1960001},
  {"SkillId":60002,"Name":"影毒突袭","CooldownMs":1960002},
  {"SkillId":60012,"Name":"毒镰扫千","CooldownMs":1960002},
  {"SkillId":60022,"Name":"刃出毒涌","CooldownMs":1960002},
  {"SkillId":60003,"Name":"噬骨毒斩","CooldownMs":1960003},
  {"SkillId":600031,"Name":"噬骨毒斩特效","CooldownMs":1960003},
  {"SkillId":60013,"Name":"毒刃穿心","CooldownMs":1960003},
  {"SkillId":600131,"Name":"毒刃穿心特效","CooldownMs":1960003},
  {"SkillId":60023,"Name":"强化毒斩","CooldownMs":1960003},
  {"SkillId":600231,"Name":"强化毒斩特效","CooldownMs":1960003},
  {"SkillId":60004,"Name":"噬毒斩","CooldownMs":1960004},
  {"SkillId":60014,"Name":"噬毒连斩","CooldownMs":1960004},
  {"SkillId":60024,"Name":"戾斩疾发","CooldownMs":1960004},
  {"SkillId":60005,"Name":"毒刃天旋","CooldownMs":1960005},
  {"SkillId":60101,"Name":"瘟疫","CooldownMs":0},
  {"SkillId":60111,"Name":"瘟疫","CooldownMs":1960111},
  {"SkillId":61001,"Name":"烈毒术","CooldownMs":1961001},
  {"SkillId":61011,"Name":"毒液践踏","CooldownMs":1961001},
  {"SkillId":61002,"Name":"毒蔓冲击","CooldownMs":1961002},
  {"SkillId":61012,"Name":"毒藤缠绕","CooldownMs":1961002},
  {"SkillId":61022,"Name":"剧毒藤蔓","CooldownMs":1961002},
  {"SkillId":61003,"Name":"爆裂毒焰","CooldownMs":1961003},
  {"SkillId":610031,"Name":"爆裂毒焰特效","CooldownMs":1961003},
  {"SkillId":61013,"Name":"毒焰升腾","CooldownMs":1961003},
  {"SkillId":610131,"Name":"毒焰升腾特效","CooldownMs":1961003},
  {"SkillId":61023,"Name":"毒焰扩散","CooldownMs":1961003},
  {"SkillId":610231,"Name":"毒焰扩散特效","CooldownMs":1961003},
  {"SkillId":61004,"Name":"罚毒之剑","CooldownMs":1961004},
  {"SkillId":61014,"Name":"罚罪","CooldownMs":1961004},
  {"SkillId":61024,"Name":"毒之影","CooldownMs":1961004},
  {"SkillId":61005,"Name":"末日毒雨","CooldownMs":1961005},
  {"SkillId":61101,"Name":"瘟疫之潮","CooldownMs":0},
  {"SkillId":61111,"Name":"瘟疫之潮","CooldownMs":1961111}
]
